readmrz/__init__.py
readmrz/cli.py
readmrz/detector.py
readmrz/reader.py
readmrz/language/mrz.traineddata
readmrz-0.0.2.dist-info/LICENSE
readmrz-0.0.2.dist-info/METADATA
readmrz-0.0.2.dist-info/WHEEL
readmrz-0.0.2.dist-info/entry_points.txt
readmrz-0.0.2.dist-info/top_level.txt
readmrz-0.0.2.dist-info/RECORD
