Metadata-Version: 2.1
Name: readmrz
Version: 0.0.2
Summary: Machine readable zone reader on ID cards
Home-page: https://github.com/egemenzeytinci/readmrz
Author: Egemen Zeytinci
Author-email: egemenzeytinci@gmail.com
Classifier: License :: OSI Approved :: MIT License
Classifier: Programming Language :: Python :: 3.7
Classifier: Programming Language :: Python :: 3.8
Classifier: Programming Language :: Python :: 3.9
Classifier: Programming Language :: Python :: 3.10
Classifier: Operating System :: MacOS
Classifier: Operating System :: POSIX :: Linux
License-File: LICENSE
Requires-Dist: mrz
Requires-Dist: opencv-python
Requires-Dist: pytesseract
